hvpdb_perms/__init__.py
hvpdb_perms/cli.py
hvpdb_perms/manager.py
hvpdb_perms-0.1.0.dist-info/METADATA
hvpdb_perms-0.1.0.dist-info/WHEEL
hvpdb_perms-0.1.0.dist-info/entry_points.txt
hvpdb_perms-0.1.0.dist-info/top_level.txt
hvpdb_perms-0.1.0.dist-info/RECORD
