Metadata-Version: 2.4
Name: hvpdb-perms
Version: 0.1.0
Summary: Permission Management Plugin for HVPDB
Author: HVPDB Team
Classifier: Programming Language :: Python :: 3
Classifier: License :: OSI Approved :: MIT License
Dynamic: author
Dynamic: classifier
Dynamic: summary
